{
  "parentUnit": "Nexos",
  "factionKeyword": [
    "genestealer cults"
  ],
  "damaged": {},
  "supremeCommander": false,
  "lore": "Engineered to share a portion of the Patriarch’s cerebral might, the Nexos can absorb the entirety of a cultist’s thoughts and experiences through physical contact. They compartmentalise millions of these snapshots, building a formidable mental map, then using it to direct cult forces like a rear-echelon officer of prodigious skill.",
  "keywords": [
    "infantry",
    "character",
    "great devourer",
    "nexos"
  ],
  "attributes": [{
    "movement": 6,
    "toughness": 3,
    "save": 5,
    "wounds": 3,
    "leadership": 7,
    "objetiveControl": 1,
    "invulnerableSave": 0
}],
  "leader": [],
  "rangedWeapons": [
    {
      "name": "Autopistol",
      "modifiers": [
        "pistol"
      ],
      "range": 12,
      "strength": 3,
      "attacks": 0,
      "ballistic-skills": 0,
      "armor-penetration": 0,
      "damage": 0,
      "singleChoice": false
    }
  ],
  "abilities": {
    "core": [
      "Deep Strike",
      "Leader"
    ],
    "faction": [
      "Battlefield Analysis: Once per turn",
      "you can select one model or unit from your army with this ability as the target of a Stratagem for 0CP",
      "even if you have already selected a model or unit from your army as the target of that Stratagem this phase.Cult Infiltration: At the start of each player’s Command phase",
      "if this model is on the battlefield",
      "you can select one Cult Ambush marker that is on the battlefield and move it up to 6\"."
    ],
    "otherAbilities": {
      "This model is equipped with:": "autopistol; close combat weapon."
    }
  }
}