{
    "parentUnit": "Kroot Carnivores",
    "factionKeyword": [
        "t’au empire"
    ],
    "damaged": {},
    "supremeCommander": false,
    "lore": "Swift and vicious, Kroot Carnivore squads employ fieldcraft and predatory instinct to close rapidly with their foes. What they lack in resilience, they more than make up for in close-ranged savagery, hammering enemies with volleys from their rifles before charging in to rip and tear their victims to gory ribbons.",
    "keywords": [
        "infantry",
        "grenades",
        "kroot",
        "carnivores"
    ],
    "attributes": [
        {
            "movement": 7,
            "toughness": 3,
            "save": 6,
            "wounds": 1,
            "leadership": 7,
            "objetiveControl": 1,
            "invulnerableSave": 0
        }
    ],
    "leader": [],
    "rangedWeapons": [
        {
            "name": "Tanglebomb launcher",
            "modifiers": [
               "blast"
            ],
            "range": 24,
            "strength": 5,
            "attacks": "d3",
            "ballistic-skills": 4,
            "armor-penetration": 0,
            "damage": 1,
            "singleChoice": false
        },
        {
            "name": "Kroot pisto",
            "modifiers": [
                "pistol"
            ],
            "range": 12,
            "strength": 4,
            "attacks": 1,
            "ballistic-skills": 4,
            "armor-penetration": 0,
            "damage": 1,
            "singleChoice": false
        },
        {
            "name": "Kroot rifle",
            "modifiers": [
                "rapid fire 1"
            ],
            "range": 24,
            "strength": 4,
            "attacks": 1,
            "ballistic-skills": 4,
            "armor-penetration": 0,
            "damage": 1,
            "singleChoice": false
        },
        {
            "name": "Kroot carbine",
            "modifiers": [
               
            ],
            "range": 18,
            "strength": 4,
            "attacks": 1,
            "ballistic-skills": 4,
            "armor-penetration": 0,
            "damage": 2,
            "singleChoice": false
        }
    ],
    "abilities": {
        "core": [
            "Scouts 7\"",
            "Stealth"
        ],
        "faction": [],
        "otherAbilities": [
            {
                "name": "Fieldcraft",
                "description": "At the end of your Command phase, if this unit is within range of an objective marker you control, that objective marker remains under your control, even if you have no models within range of it, until your opponent controls it at the start or end of any turn."
            }
        ]
    },
    "wargear": [],
    "meleeWeapons": [
        {
            "name": "Close combat weapon",
            "attacks": 2,
            "weapons-skills": 3,
            "strength": 4,
            "armor-penetration": 0,
            "damage": 1,
            "modifiers": []
        }
    ],
    "additionalParameter": {
        "title": "Bodyguard",
        "abilities": [
            {
                "name": "",
                "description": "If this unit has a Starting Strength of 20, you can attach up to two Leader units to it instead of one, provided those Leaders are not duplicates (e.g. you cannot attach two WAR SHAPERS to this unit). If you do, and this unit is destroyed, the Leader units attached to it become separate units with their original Starting Strengths."
            }
        ]
    },
    "unitComposition": [
        {
            "unitType": "Long-quill",
            "minQuantity": 1,
            "maxQuantity": 1,
            "equipment": [
                "Kroot pistol","Kroot rifle","close combat weapon."
            ]
        },
        {
            "unitType": "Kroot Carnivores",
            "minQuantity": 9,
            "maxQuantity": 19,
            "equipment": [
                "Kroot rifle","close combat weapon."
            ]
        }
    ],
    "options": [
        {
            "count": [
                1,9
            ],
            "points": 65
        },
        {
            "count": [
                1,19
            ],
            "points": 130
        }
    ]
}