{
    "parentUnit": "Cadian Castellan",
    "factionKeyword": [
        "astra militarum"
    ],
    "damaged": {},
    "supremeCommander": false,
    "lore": "Strategic senior officers often ranking as Captains or Colonels, Cadian Castellans are authoritative leaders of the fallen world’s forces. Bearing a panoply of armaments and insignia that mark their high office, they wield their weapons as skilfully as they command the soldiers beneath them.",
    "keywords": [
        "infantry",
        "character",
        "imperium",
        "grenades",
        "officer",
        "cadian",
        "cadian castellan"
    ],
    "attributes": [
        {
            "movement": 6,
            "toughness": 3,
            "save": 5,
            "wounds": 4,
            "leadership": 7,
            "objetiveControl": 1,
            "invulnerableSave": 5
        }
    ],
    "leader": [
        "Cadian Shock Troops",
        "Infantry Squad",
        "Kasrkin"
    ],
    "rangedWeapons": [
        {
            "name": "Bolt pistol",
            "modifiers": [
                "pistol"
            ],
            "range": 12,
            "strength": 4,
            "attacks": 1,
            "ballistic-skills": 3,
            "armor-penetration": 0,
            "damage": 1,
            "singleChoice": false
        },
        {
            "name": "Boltgun",
            "modifiers": [
                "rapid fire 1"
            ],
            "range": 24,
            "strength": 4,
            "attacks": 1,
            "ballistic-skills": 3,
            "armor-penetration": 0,
            "damage": 1,
            "singleChoice": false
        },
        {
            "name": "Laspistol",
            "modifiers": [
                "pistol"
            ],
            "range": 12,
            "strength": 3,
            "attacks": 1,
            "ballistic-skills": 4,
            "armor-penetration": 0,
            "damage": 1,
            "singleChoice": false
        },
        {
            "name": "Plasma pistol - standard",
            "modifiers": [
                "pistol"
            ],
            "range": 12,
            "strength": 7,
            "attacks": 1,
            "ballistic-skills": 3,
            "armor-penetration": 2,
            "damage": 1,
            "singleChoice": true
        },
        {
            "name": "Plasma pistol - supercharge",
            "modifiers": [
                "hazardous",
                "pistol"
            ],
            "range": 12,
            "strength": 8,
            "attacks": 1,
            "ballistic-skills": 3,
            "armor-penetration": 2,
            "damage": 3,
            "singleChoice": true
        }
    ],
    "abilities": {
        "core": [
            "Leader"
        ],
        "faction": [
            "Voice of Command"
        ],
        "otherAbilities": [
            {
                "name": "Senior Officer:",
                "description": "While this model is leading a unit, ranged weapons equipped by models in that unit have the [SUSTAINED HITS 1] ability."
            },
            {
                "name": "Get Back in the Fight:",
                "description": "While this model is leading a unit, that unit is eligible to shoot in a turn in which it Fell Back ."
            }
        ]
    },
    "wargear": [
        {"miniature":"cadian castellan",
            "description": "This model’s chainsword can be replaced with one of the following",
            "items": [
                "boltgun",
                "power fist",
                "power weapon"
            ]
        },
        {"miniature":"cadian castellan",
            "description": "This model’s laspistol can be replaced with one of the following",
            "items": [
                "bolt pistol",
                "plasma pistol"
            ]
        }
    ],
    "meleeWeapons": [
        {
            "name": "Chainsword",
            "modifiers": [],
            "attacks": 5,
            "weapons-skills": 3,
            "strength": 3,
            "armor-penetration": 0,
            "damage": 1
        },
        {
            "name": "Power fist",
            "modifiers": [],
            "attacks": 3,
            "weapons-skills": 3,
            "strength": 6,
            "armor-penetration": 2,
            "damage": 2
        },
        {
            "name": "Power weapon",
            "modifiers": [],
            "attacks": 4,
            "weapons-skills": 3,
            "strength": 4,
            "armor-penetration": 2,
            "damage": 1
        }
    ],
    "additionalParameter": {},
    "unitComposition": [
        {
            "unitType": "Cadian Castellan",
            "minQuantity": 1,
            "maxQuantity": 1,
            "equipment": [
                "laspistol",
                "chainsword"
            ]
        }
    ],
    "options": [
        {
            "count": [
                1
            ],
            "points": 45
        }
    ]
}